Workbook

Sheet Overview
A1: Sport Mate — Feature & Role Specification
A3: Project | B3: Sport Mate — sportswear e-commerce mobile application (PRM392)
A4: Version | B4: 1.1
A5: Date | B5: 2026-10-14
A6: Scope | B6: 78 features (F01–F78), mapped one-to-one to use cases UC-001–UC-078
A7: Schedule | B7: Start 07/09/2026 · Interaction 1 due 13/10/2026 · Interaction 2 due 21/10/2026 · Interaction 3 due 27/10/2026
A8: Team | B8: Nguyễn Hoàng Minh · Lê Huỳnh Nhựt Khanh · Huỳnh Trần Phước Sang · Trần Thị Hồng Mai · Trương Đoàn Minh Phúc
A9: Tech stack | B9: Flutter (mobile) · ASP.NET Core Web API (REST/JSON, JWT) · SQL Server (EF Core)
A10: Source documents | B10: USE_CASES.md · BUSINESS_RULES.md · API_DESIGN.md · MOBILE_ARCHITECTURE.md · BACKEND_ARCHITECTURE.md
A12: How to use this workbook
A13: • Features sheet: one row per feature (F01–F78) with Interaction (L), Deadline (M), Status (N) and Assignee (O).
A14: • Update Status as work progresses; the progress tables here and on the Delivery Plan sheet recalculate automatically.
A15: • API paths are relative to /api/v1. "(proposed)" marks endpoints not defined in API_DESIGN.md.
A16: • /admin/* endpoints are shared by Staff and Admin; the app shows or hides features by role and the API checks every request.
A17: • Priority (Must / Should / Could) is a proposal; it is not defined in the source documents.
A18: Cell to fill in
A20: Progress by module
A21: Module | B21: Feature IDs | C21: Features | D21: Done | E21: % done | F21: Roles involved
A22: Authentication | B22: F01–F05 | C22: =COUNTIF(Features!$B$2:$B$79,A22) -> 5 | D22: =COUNTIFS(Features!$B$2:$B$79,A22,Features!$N$2:$N$79,"Done") -> 5 | E22: =IF(C22=0,0,D22/C22) -> 1 | F22: Guest, Customer, Staff, Admin
A23: User & Profile | B23: F06–F17 | C23: =COUNTIF(Features!$B$2:$B$79,A23) -> 12 | D23: =COUNTIFS(Features!$B$2:$B$79,A23,Features!$N$2:$N$79,"Done") -> 4 | E23: =IF(C23=0,0,D23/C23) -> 0.33333333 | F23: Customer, Staff, Admin
A24: Product & Catalog | B24: F18–F42 | C24: =COUNTIF(Features!$B$2:$B$79,A24) -> 25 | D24: =COUNTIFS(Features!$B$2:$B$79,A24,Features!$N$2:$N$79,"Done") -> 18 | E24: =IF(C24=0,0,D24/C24) -> 0.72 | F24: Guest, Customer, Staff, Admin
A25: Inventory | B25: F43–F45 | C25: =COUNTIF(Features!$B$2:$B$79,A25) -> 3 | D25: =COUNTIFS(Features!$B$2:$B$79,A25,Features!$N$2:$N$79,"Done") -> 0 | E25: =IF(C25=0,0,D25/C25) -> 0 | F25: Staff, Admin
A26: Shopping Cart | B26: F46–F50 | C26: =COUNTIF(Features!$B$2:$B$79,A26) -> 5 | D26: =COUNTIFS(Features!$B$2:$B$79,A26,Features!$N$2:$N$79,"Done") -> 5 | E26: =IF(C26=0,0,D26/C26) -> 1 | F26: Customer
A27: Checkout & Orders | B27: F51–F57 | C27: =COUNTIF(Features!$B$2:$B$79,A27) -> 7 | D27: =COUNTIFS(Features!$B$2:$B$79,A27,Features!$N$2:$N$79,"Done") -> 2 | E27: =IF(C27=0,0,D27/C27) -> 0.28571429 | F27: Customer, Staff, Admin
A28: Payments | B28: F58–F60 | C28: =COUNTIF(Features!$B$2:$B$79,A28) -> 3 | D28: =COUNTIFS(Features!$B$2:$B$79,A28,Features!$N$2:$N$79,"Done") -> 0 | E28: =IF(C28=0,0,D28/C28) -> 0 | F28: Customer, Staff, Admin
A29: Coupons | B29: F61–F67 | C29: =COUNTIF(Features!$B$2:$B$79,A29) -> 7 | D29: =COUNTIFS(Features!$B$2:$B$79,A29,Features!$N$2:$N$79,"Done") -> 0 | E29: =IF(C29=0,0,D29/C29) -> 0 | F29: Customer, Admin
A30: Reviews | B30: F68–F72 | C30: =COUNTIF(Features!$B$2:$B$79,A30) -> 5 | D30: =COUNTIFS(Features!$B$2:$B$79,A30,Features!$N$2:$N$79,"Done") -> 0 | E30: =IF(C30=0,0,D30/C30) -> 0 | F30: Guest, Customer, Staff, Admin
A31: Wishlist | B31: F73–F75 | C31: =COUNTIF(Features!$B$2:$B$79,A31) -> 3 | D31: =COUNTIFS(Features!$B$2:$B$79,A31,Features!$N$2:$N$79,"Done") -> 3 | E31: =IF(C31=0,0,D31/C31) -> 1 | F31: Customer
A32: Reports | B32: F76–F78 | C32: =COUNTIF(Features!$B$2:$B$79,A32) -> 3 | D32: =COUNTIFS(Features!$B$2:$B$79,A32,Features!$N$2:$N$79,"Done") -> 0 | E32: =IF(C32=0,0,D32/C32) -> 0 | F32: Admin
A33: Total | B33: F01–F78 | C33: =SUM(C22:C32) -> 78 | D33: =SUM(D22:D32) -> 37 | E33: =IF(C33=0,0,D33/C33) -> 0.47435897 | F33: Guest, Customer, Staff, Admin

Sheet Delivery Plan
A1: Delivery Plan
A2: Project start | B2: 46272
A4: Interaction schedule
A5: Interaction | B5: Start | C5: Deadline | D5: Status | E5: Features | F5: Total | G5: Done | H5: Processing | I5: Not Start
A6: Interaction 1 | B6: =$B$2 -> 46272 | C6: 46308 | D6: Done | E6: F01–F09, F18–F30, F38–F42, F46–F52, F73–F75 | F6: =COUNTIF(Features!$L$2:$L$79,1) -> 37 | G6: =COUNTIFS(Features!$L$2:$L$79,1,Features!$N$2:$N$79,"Done") -> 37 | H6: =COUNTIFS(Features!$L$2:$L$79,1,Features!$N$2:$N$79,"Processing") -> 0 | I6: =COUNTIFS(Features!$L$2:$L$79,1,Features!$N$2:$N$79,"Not Start") -> 0
A7: Interaction 2 | B7: =C6+1 -> 46309 | C7: 46316 | D7: Processing | E7: F10–F12, F31–F33, F43–F45, F53–F67 | F7: =COUNTIF(Features!$L$2:$L$79,2) -> 24 | G7: =COUNTIFS(Features!$L$2:$L$79,2,Features!$N$2:$N$79,"Done") -> 0 | H7: =COUNTIFS(Features!$L$2:$L$79,2,Features!$N$2:$N$79,"Processing") -> 24 | I7: =COUNTIFS(Features!$L$2:$L$79,2,Features!$N$2:$N$79,"Not Start") -> 0
A8: Interaction 3 | B8: =C7+1 -> 46317 | C8: 46322 | D8: Not Start | E8: F13–F17, F34–F37, F68–F72, F76–F78 | F8: =COUNTIF(Features!$L$2:$L$79,3) -> 17 | G8: =COUNTIFS(Features!$L$2:$L$79,3,Features!$N$2:$N$79,"Done") -> 0 | H8: =COUNTIFS(Features!$L$2:$L$79,3,Features!$N$2:$N$79,"Processing") -> 0 | I8: =COUNTIFS(Features!$L$2:$L$79,3,Features!$N$2:$N$79,"Not Start") -> 17
A9: Total | B9: =B6 -> 46272 | C9: =C8 -> 46322 | E9: F01–F78 | F9: =SUM(F6:F8) -> 78 | G9: =SUM(G6:G8) -> 37 | H9: =SUM(H6:H8) -> 24 | I9: =SUM(I6:I8) -> 17
A11: Team assignment
A12: Member | B12: GitHub | C12: Total | D12: % done | E12: Features | F12: Done | G12: Processing | H12: Not Start
A13: Nguyễn Hoàng Minh | B13: Minh2005 | C13: =COUNTIF(Features!$O$2:$O$79,A13) -> 17 | D13: =IF(C13=0,0,F13/C13) -> 0.52941176 | E13: F01–F17 | F13: =COUNTIFS(Features!$O$2:$O$79,A13,Features!$N$2:$N$79,"Done") -> 9 | G13: =COUNTIFS(Features!$O$2:$O$79,A13,Features!$N$2:$N$79,"Processing") -> 3 | H13: =COUNTIFS(Features!$O$2:$O$79,A13,Features!$N$2:$N$79,"Not Start") -> 5
A14: Lê Huỳnh Nhựt Khanh | B14: lehuynhnhutkhanh2004 | C14: =COUNTIF(Features!$O$2:$O$79,A14) -> 15 | D14: =IF(C14=0,0,F14/C14) -> 0.33333333 | E14: F26–F37, F65–F67 | F14: =COUNTIFS(Features!$O$2:$O$79,A14,Features!$N$2:$N$79,"Done") -> 5 | G14: =COUNTIFS(Features!$O$2:$O$79,A14,Features!$N$2:$N$79,"Processing") -> 6 | H14: =COUNTIFS(Features!$O$2:$O$79,A14,Features!$N$2:$N$79,"Not Start") -> 4
A15: Huỳnh Trần Phước Sang | B15: sengggggg | C15: =COUNTIF(Features!$O$2:$O$79,A15) -> 21 | D15: =IF(C15=0,0,F15/C15) -> 0.61904762 | E15: F18–F25, F46–F50, F56–F60, F76–F78 | F15: =COUNTIFS(Features!$O$2:$O$79,A15,Features!$N$2:$N$79,"Done") -> 13 | G15: =COUNTIFS(Features!$O$2:$O$79,A15,Features!$N$2:$N$79,"Processing") -> 5 | H15: =COUNTIFS(Features!$O$2:$O$79,A15,Features!$N$2:$N$79,"Not Start") -> 3
A16: Trần Thị Hồng Mai | B16: HM126-m | C16: =COUNTIF(Features!$O$2:$O$79,A16) -> 12 | D16: =IF(C16=0,0,F16/C16) -> 0.25 | E16: F61–F64, F68–F75 | F16: =COUNTIFS(Features!$O$2:$O$79,A16,Features!$N$2:$N$79,"Done") -> 3 | G16: =COUNTIFS(Features!$O$2:$O$79,A16,Features!$N$2:$N$79,"Processing") -> 4 | H16: =COUNTIFS(Features!$O$2:$O$79,A16,Features!$N$2:$N$79,"Not Start") -> 5
A17: Trương Đoàn Minh Phúc | B17: nilernous | C17: =COUNTIF(Features!$O$2:$O$79,A17) -> 13 | D17: =IF(C17=0,0,F17/C17) -> 0.53846154 | E17: F38–F45, F51–F55 | F17: =COUNTIFS(Features!$O$2:$O$79,A17,Features!$N$2:$N$79,"Done") -> 7 | G17: =COUNTIFS(Features!$O$2:$O$79,A17,Features!$N$2:$N$79,"Processing") -> 6 | H17: =COUNTIFS(Features!$O$2:$O$79,A17,Features!$N$2:$N$79,"Not Start") -> 0
A18: Total | C18: =SUM(C13:C17) -> 78 | D18: =IF(C18=0,0,F18/C18) -> 0.47435897 | E18: F01–F78 | F18: =SUM(F13:F17) -> 37 | G18: =SUM(G13:G17) -> 24 | H18: =SUM(H13:H17) -> 17
A19: =IF(C18=COUNTA(Features!$C$2:$C$79),"All features assigned","Unassigned features: "&(COUNTA(Features!$C$2:$C$79)-C18)) -> All features assigned

Sheet Features
A1: No. | B1: Module | C1: Feature ID | D1: Use Case ID | E1: Feature Name | F1: Description | G1: Roles | H1: API Endpoint | I1: Mobile Screen | J1: Business Rules | K1: Priority | L1: Interaction | M1: Deadline | N1: Status | O1: Assignee
A2: 1 | B2: Authentication | C2: F01 | D2: UC-001 | E2: Register account | F2: Guest enters name, email and password; API validates input and password policy, checks email uniqueness, hashes the password and creates a Customer account. | G2: Guest | H2: POST /auth/register | I2: Register | J2: BR-008, BR-009, BR-071, BR-072 | K2: Must | L2: 1 | M2: 46308 | N2: Done | O2: Nguyễn Hoàng Minh
A3: 2 | B3: Authentication | C3: F02 | D3: UC-002 | E3: Sign in | F3: Guest submits credentials; API verifies them and account status, then issues a JWT and returns safe user info and role (used by the app to show/hide features). | G3: Guest | H3: POST /auth/login | I3: Login | J3: BR-006, BR-007, BR-078 | K3: Must | L3: 1 | M3: 46308 | N3: Done | O3: Nguyễn Hoàng Minh
A4: 3 | B4: Authentication | C4: F03 | D4: UC-003 | E4: Sign out | F4: User signs out; app clears local auth state and API revokes the refresh token/session if supported. | G4: Customer, Staff, Admin | H4: POST /auth/logout | I4: Profile | J4: BR-077, BR-078 | K4: Must | L4: 1 | M4: 46308 | N4: Done | O4: Nguyễn Hoàng Minh
A5: 4 | B5: Authentication | C5: F04 | D5: UC-004 | E5: Request password reset | F5: Guest submits an email; API returns a generic response and starts a time-limited reset process for an eligible account without disclosing whether the email exists. | G5: Guest | H5: POST /auth/forgot-password | I5: Forgot Password | J5: BR-010, BR-072 | K5: Should | L5: 1 | M5: 46308 | N5: Done | O5: Nguyễn Hoàng Minh
A6: 5 | B6: Authentication | C6: F05 | D6: UC-005 | E6: Reset password using token | F6: Guest submits a valid reset token and new password; API validates both, updates the password hash and invalidates the token. | G6: Guest | H6: POST /auth/reset-password | I6: Reset Password | J6: BR-009, BR-010 | K6: Should | L6: 1 | M6: 46308 | N6: Done | O6: Nguyễn Hoàng Minh
A7: 6 | B7: User & Profile | C7: F06 | D7: UC-006 | E7: Change password | F7: User submits current and new password; API verifies the current one, validates the new one, updates the hash and applies the session-revocation policy. | G7: Customer, Staff, Admin | H7: PUT /users/me/password | I7: Profile › Change Password | J7: BR-009, BR-011, BR-078 | K7: Must | L7: 1 | M7: 46308 | N7: Done | O7: Nguyễn Hoàng Minh
A8: 7 | B8: User & Profile | C8: F07 | D8: UC-007 | E8: View own profile | F8: App requests the current profile; API resolves identity from JWT claims and returns the allowed fields. | G8: Customer, Staff, Admin | H8: GET /users/me | I8: Profile | J8: BR-006, BR-011, BR-078 | K8: Must | L8: 1 | M8: 46308 | N8: Done | O8: Nguyễn Hoàng Minh
A9: 8 | B9: User & Profile | C9: F08 | D9: UC-008 | E9: Update own profile | F9: User edits allowed profile fields; API updates only the current user's record. Role/status cannot be changed here. | G9: Customer, Staff, Admin | H9: PUT /users/me | I9: Profile › Edit Profile | J9: BR-006, BR-011, BR-071 | K9: Must | L9: 1 | M9: 46308 | N9: Done | O9: Nguyễn Hoàng Minh
A10: 9 | B10: User & Profile | C10: F09 | D10: UC-009 | E10: Create delivery address | F10: Customer submits address fields; API validates and creates an address owned by the current Customer. | G10: Customer | H10: POST /users/me/addresses | I10: Address Management | J10: BR-012, BR-071 | K10: Must | L10: 1 | M10: 46308 | N10: Done | O10: Nguyễn Hoàng Minh
A11: 10 | B11: User & Profile | C11: F10 | D11: UC-010 | E11: List own delivery addresses | F11: Customer views the address book; API returns only addresses owned by the current Customer. | G11: Customer | H11: GET /users/me/addresses | I11: Address Management | J11: BR-006, BR-012 | K11: Must | L11: 2 | M11: 46316 | N11: Processing | O11: Nguyễn Hoàng Minh
A12: 11 | B12: User & Profile | C12: F11 | D12: UC-011 | E12: Update own delivery address | F12: Customer edits an address; API verifies ownership and updates it. Historical order address snapshots are not changed. | G12: Customer | H12: PUT /users/me/addresses/{id} | I12: Address Management | J12: BR-012, BR-013 | K12: Must | L12: 2 | M12: 46316 | N12: Processing | O12: Nguyễn Hoàng Minh
A13: 12 | B13: User & Profile | C13: F12 | D13: UC-012 | E13: Delete own delivery address | F13: Customer deletes an address; API verifies ownership and deletes or deactivates it safely without affecting order snapshots. | G13: Customer | H13: DELETE /users/me/addresses/{id} | I13: Address Management | J13: BR-012, BR-013 | K13: Must | L13: 2 | M13: 46316 | N13: Processing | O13: Nguyễn Hoàng Minh
... A79: 78 | B79: Reports | C79: F78 | D79: UC-078 | E79: View best-selling products report | F79: Admin views products ranked by the agreed quantity/revenue definition for a period. | G79: Admin | H79: GET /admin/reports/top-products | I79: Admin Panel › Dashboard | J79: BR-067, BR-069, BR-070 | K79: Should | L79: 3 | M79: 46322 | N79: Not Start | O79: Huỳnh Trần Phước Sang

Sheet Roles
A1: Role | B1: Type | C1: Description | D1: Mobile area
A2: Guest | B2: Unauthenticated actor (not stored) | C2: Visitor who may register, sign in, reset a password and browse, search, filter and sort the public catalog and reviews. | D2: Auth screens, Home, Product List / Detail, Search
A3: Customer | B3: Authenticated role | C3: Registered shopper who manages their own profile, addresses, cart, orders, payments, wishlist and eligible reviews. | D3: Customer app (bottom navigation)
A4: Staff | B4: Authenticated role | C4: Operational user who maintains catalog and inventory, processes orders, confirms manual bank transfers and moderates reviews. Cannot manage roles, users, coupons or reports. | D4: Admin Panel (operational items only) + Profile
A5: Admin | B5: Authenticated role | C5: Administrator with all Staff capabilities plus user and role management, coupon management and reports. | D5: Admin Panel (all items) + Profile

Sheet Authorization
A1: Capability | B1: Guest | C1: Customer | D1: Staff | E1: Admin
A2: Browse public catalog and reviews | B2: Yes | C2: Yes | D2: Yes | E2: Yes
A3: Manage own profile and password | B3: No | C3: Yes | D3: Yes | E3: Yes
A4: Manage own addresses, cart, orders, payments | B4: No | C4: Yes | D4: No by default | E4: No by default
A5: Manage own wishlist and reviews | B5: No | C5: Yes | D5: No | E5: No
A6: Manage catalog (categories, brands, products, variants, images) | B6: No | C6: No | D6: Yes | E6: Yes
A7: Manage inventory | B7: No | C7: No | D7: Yes | E7: Yes
A8: Process all orders | B8: No | C8: No | D8: Yes | E8: Yes
A9: Confirm manual bank transfer | B9: No | C9: No | D9: Yes | E9: Yes
A10: Moderate reviews | B10: No | C10: No | D10: Yes | E10: Yes
A11: Manage coupons | B11: No | C11: No | D11: No | E11: Yes
A12: Manage users and roles | B12: No | C12: No | D12: No | E12: Yes
A13: View dashboard and reports | B13: No | C13: No | D13: No | E13: Yes

Sheet Screen Visibility
A1: Screen / Navigation item | B1: Features | C1: Guest | D1: Customer | E1: Staff | F1: Admin
A2: Login, Register, Forgot / Reset Password | B2: F01, F02, F04, F05 | C2: ● | D2: – | E2: – | F2: –
A3: Home, Product List, Categories & Search | B3: F38, F40–F42 | C3: ● | D3: ● | E3: ● | F3: ●
A4: Product Detail | B4: F39, F69 | C4: ● | D4: ● | E4: ● | F4: ●
A5: Product Detail › Add to Cart / Add to Wishlist | B5: F47, F74 | C5: Prompt | D5: ● | E5: – | F5: –
A6: Product Reviews › Write / Edit / Delete review | B6: F68, F70, F71 | C6: Prompt | D6: ● | E6: – | F6: –
A7: Cart | B7: F46, F48–F50 | C7: – | D7: ● | E7: – | F7: –
A8: Checkout (address, coupon, payment) | B8: F51, F52, F59, F65–F67 | C8: – | D8: ● | E8: – | F8: –
A9: Order History, Order Detail | B9: F53–F55, F58 | C9: – | D9: ● | E9: – | F9: –
A10: Wishlist | B10: F73–F75 | C10: – | D10: ● | E10: – | F10: –
A11: Profile, Change Password, Sign Out | B11: F03, F06–F08 | C11: – | D11: ● | E11: ● | F11: ●
A12: Address Management | B12: F09–F12 | C12: – | D12: ● | E12: – | F12: –
... A19: Admin Panel › Dashboard & Reports | B19: F76–F78 | C19: – | D19: – | E19: – | F19: ●
A21: ● shown · – hidden · Prompt: visible but asks a Guest to sign in

Sheet Business Rules
A1: ID | B1: Rule | C1: Group
A2: BR-001 | B2: Supported roles | C2: Roles and Access Control
A3: BR-002 | B3: Public access | C3: Roles and Access Control
A4: BR-003 | B4: Customer ownership | C4: Roles and Access Control
A5: BR-004 | B5: Staff permissions | C5: Roles and Access Control
A6: BR-005 | B6: Admin permissions | C6: Roles and Access Control
A7: BR-006 | B7: Identity source | C7: Roles and Access Control
A8: BR-007 | B8: Account status | C8: Roles and Access Control
A9: BR-008 | B9: Unique email | C9: Authentication and User Data
A10: BR-009 | B10: Password storage | C10: Authentication and User Data
A11: BR-010 | B11: Password reset | C11: Authentication and User Data
A12: BR-011 | B12: Profile update | C12: Authentication and User Data
... A79: BR-078 | B79: Authentication enforcement | C79: API and Data Integrity
